pypeprompts/__init__.py
pypeprompts/config/config.py
pypeprompts/main.py
pypeprompts-0.0.7.dist-info/LICENSE
pypeprompts-0.0.7.dist-info/METADATA
pypeprompts-0.0.7.dist-info/WHEEL
pypeprompts-0.0.7.dist-info/RECORD
