Metadata-Version: 2.1
Name: pypeprompts
Version: 0.0.7
Summary: A simple tracker for OpenAI API calls for Pype App
License: MIT
Author: dhruv
Author-email: dhruv@pypeai.com
Requires-Python: >=3.8.1,<4.0
Classifier: License :: OSI Approved :: MIT License
Classifier: Programming Language :: Python :: 3
Classifier: Programming Language :: Python :: 3.9
Classifier: Programming Language :: Python :: 3.10
Classifier: Programming Language :: Python :: 3.11
Classifier: Programming Language :: Python :: 3.12
Requires-Dist: aiohttp (>=3.10.3,<4.0.0)
Requires-Dist: pydantic (>=2.8.2,<3.0.0)
Requires-Dist: pytest-asyncio (>=0.23.8,<0.24.0)
Requires-Dist: python-dotenv (>=1.0.1,<2.0.0)
Requires-Dist: requests (>=2.25.1,<3.0.0)
Requires-Dist: responses (>=0.25.3,<0.26.0)
